bulk_support/__init__.py
bulk_support/__version__.py
bulk_support/bulk_states.py
bulk_support/bulk_support.py
bulk_support/csv_adapter.py
bulk_support/util.py
bulk_support-0.3.dist-info/LICENSE
bulk_support-0.3.dist-info/METADATA
bulk_support-0.3.dist-info/WHEEL
bulk_support-0.3.dist-info/top_level.txt
bulk_support-0.3.dist-info/RECORD
