Metadata-Version: 2.1
Name: bulk-support
Version: 0.3
Summary: Python interface to the Salesforce.com Bulk API.
Home-page: https://github.com/rmohamedfazil/sfdc-bulk
Author: Mohamed Fazil R
Author-email: rmohamedfazil@gmail.com
License: MIT
Platform: UNKNOWN
Classifier: Development Status :: 5 - Production/Stable
Classifier: Intended Audience :: Developers
Classifier: Natural Language :: English
Classifier: License :: OSI Approved :: MIT License
Classifier: Programming Language :: Python
Classifier: Programming Language :: Python :: 2.7
Classifier: Programming Language :: Python :: 3.3
Classifier: Programming Language :: Python :: 3.4
Classifier: Programming Language :: Python :: 3.5
Classifier: Programming Language :: Python :: 3.6
Classifier: Programming Language :: Python :: 3.7
Requires-Dist: six
Requires-Dist: requests (>=2.2.1)
Requires-Dist: unicodecsv (>=0.14.1)
Requires-Dist: simple-salesforce (>=0.69)
